[
  {
    "ticker": "TSLA",
    "tweet_id": "2048271866914083172"
  },
  {
    "ticker": "TSLA",
    "tweet_id": "2048271594120729021"
  },
  {
    "ticker": "TSLA",
    "tweet_id": "2048271324577952130"
  },
  {
    "ticker": "TSLA",
    "tweet_id": "2048271232047386949"
  },
  {
    "ticker": "TSLA",
    "tweet_id": "2048270511705145692"
  },
  {
    "ticker": "TSLA",
    "tweet_id": "2048270411175956621"
  },
  {
    "ticker": "TSLA",
    "tweet_id": "2048270328749576690"
  },
  {
    "ticker": "TSLA",
    "tweet_id": "2048246412534600143"
  },
  {
    "ticker": "TSLA",
    "tweet_id": "2048234907965526306"
  },
  {
    "ticker": "TSLA",
    "tweet_id": "2048234603165491423"
  },
  {
    "ticker": "TSLA",
    "tweet_id": "2048233500151521491"
  },
  {
    "ticker": "TSLA",
    "tweet_id": "2048232203381776749"
  },
  {
    "ticker": "TSLA",
    "tweet_id": "2048227580050886861"
  },
  {
    "ticker": "TSLA",
    "tweet_id": "2048154657483079769"
  },
  {
    "ticker": "TSLA",
    "tweet_id": "2048151716927807806"
  },
  {
    "ticker": "TSLA",
    "tweet_id": "2048147476016758872"
  },
  {
    "ticker": "TSLA",
    "tweet_id": "2048117526538621337"
  },
  {
    "ticker": "TSLA",
    "tweet_id": "2048117098941992976"
  },
  {
    "ticker": "TSLA",
    "tweet_id": "2048105834798866644"
  },
  {
    "ticker": "TSLA",
    "tweet_id": "2048105666284261437"
  },
  {
    "ticker": "TSLA",
    "tweet_id": "2048105333155860935"
  },
  {
    "ticker": "TSLA",
    "tweet_id": "2048098485807755729"
  },
  {
    "ticker": "TSLA",
    "tweet_id": "2048041081032294845"
  },
  {
    "ticker": "TSLA",
    "tweet_id": "2048040275327537520"
  },
  {
    "ticker": "TSLA",
    "tweet_id": "2048040191630135355"
  },
  {
    "ticker": "TSLA",
    "tweet_id": "2048039569195446397"
  },
  {
    "ticker": "TSLA",
    "tweet_id": "2048039351863406736"
  },
  {
    "ticker": "TSLA",
    "tweet_id": "2048035037057048824"
  },
  {
    "ticker": "TSLA",
    "tweet_id": "2048034956908077173"
  },
  {
    "ticker": "TSLA",
    "tweet_id": "2048019742057762964"
  },
  {
    "ticker": "TSLA",
    "tweet_id": "2048017984023646379"
  },
  {
    "ticker": "TSLA",
    "tweet_id": "2048016512015847438"
  },
  {
    "ticker": "TSLA",
    "tweet_id": "2048016137695138021"
  },
  {
    "ticker": "TSLA",
    "tweet_id": "2048015132500934711"
  },
  {
    "ticker": "TSLA",
    "tweet_id": "2048007645471125653"
  },
  {
    "ticker": "TSLA",
    "tweet_id": "2048009661400457412"
  },
  {
    "ticker": "TSLA",
    "tweet_id": "2048009215738839242"
  },
  {
    "ticker": "TSLA",
    "tweet_id": "2048008745406386266"
  },
  {
    "ticker": "TSLA",
    "tweet_id": "2048008024887849467"
  },
  {
    "ticker": "TSLA",
    "tweet_id": "2048007041688432706"
  },
  {
    "ticker": "TSLA",
    "tweet_id": "2048006970158846411"
  },
  {
    "ticker": "TSLA",
    "tweet_id": "2048006829532135533"
  },
  {
    "ticker": "TSLA",
    "tweet_id": "2048006372487295473"
  },
  {
    "ticker": "TSLA",
    "tweet_id": "2048006216559812916"
  },
  {
    "ticker": "TSLA",
    "tweet_id": "2048005975714463935"
  },
  {
    "ticker": "TSLA",
    "tweet_id": "2048005882013688221"
  },
  {
    "ticker": "TSLA",
    "tweet_id": "2048005498784358695"
  },
  {
    "ticker": "TSLA",
    "tweet_id": "2048001102914761205"
  },
  {
    "ticker": "TSLA",
    "tweet_id": "2048000891152650646"
  },
  {
    "ticker": "TSLA",
    "tweet_id": "2047927579626131916"
  },
  {
    "ticker": "TSLA",
    "tweet_id": "2047927315070324771"
  },
  {
    "ticker": "TSLA",
    "tweet_id": "2047927162229915918"
  },
  {
    "ticker": "TSLA",
    "tweet_id": "2047922225353728189"
  },
  {
    "ticker": "TSLA",
    "tweet_id": "2047919711225020570"
  },
  {
    "ticker": "TSLA",
    "tweet_id": "2047882728972939595"
  },
  {
    "ticker": "TSLA",
    "tweet_id": "2047877668922593700"
  },
  {
    "ticker": "TSLA",
    "tweet_id": "2047877294476116184"
  },
  {
    "ticker": "TSLA",
    "tweet_id": "2047876733991260511"
  },
  {
    "ticker": "TSLA",
    "tweet_id": "2047876662356844756"
  },
  {
    "ticker": "TSLA",
    "tweet_id": "2047838913646248162"
  },
  {
    "ticker": "TSLA",
    "tweet_id": "2047837348323553342"
  },
  {
    "ticker": "TSLA",
    "tweet_id": "2047832955880685851"
  },
  {
    "ticker": "TSLA",
    "tweet_id": "2047830790114033779"
  },
  {
    "ticker": "TSLA",
    "tweet_id": "2047824840426652061"
  },
  {
    "ticker": "TSLA",
    "tweet_id": "2047824744112947574"
  },
  {
    "ticker": "TSLA",
    "tweet_id": "2047824192293499044"
  },
  {
    "ticker": "TSLA",
    "tweet_id": "2047822018549313681"
  },
  {
    "ticker": "TSLA",
    "tweet_id": "2047820910720438485"
  },
  {
    "ticker": "TSLA",
    "tweet_id": "2047796763315286503"
  },
  {
    "ticker": "TSLA",
    "tweet_id": "2047796728439734318"
  },
  {
    "ticker": "TSLA",
    "tweet_id": "2047796518720323929"
  },
  {
    "ticker": "TSLA",
    "tweet_id": "2047795892993019909"
  },
  {
    "ticker": "TSLA",
    "tweet_id": "2047795651791171997"
  },
  {
    "ticker": "TSLA",
    "tweet_id": "2047790398102438251"
  },
  {
    "ticker": "TSLA",
    "tweet_id": "2047757400866963632"
  },
  {
    "ticker": "TSLA",
    "tweet_id": "2047735226756190282"
  },
  {
    "ticker": "TSLA",
    "tweet_id": "2047710114581532958"
  },
  {
    "ticker": "TSLA",
    "tweet_id": "2047710056297451832"
  },
  {
    "ticker": "TSLA",
    "tweet_id": "2047709618361803027"
  },
  {
    "ticker": "TSLA",
    "tweet_id": "2047705980771975596"
  },
  {
    "ticker": "TSLA",
    "tweet_id": "2047705842292781068"
  },
  {
    "ticker": "TSLA",
    "tweet_id": "2047704232015626330"
  },
  {
    "ticker": "TSLA",
    "tweet_id": "2047704005095354775"
  },
  {
    "ticker": "TSLA",
    "tweet_id": "2047703663649640868"
  },
  {
    "ticker": "TSLA",
    "tweet_id": "2047703022890062004"
  },
  {
    "ticker": "TSLA",
    "tweet_id": "2047702937691164906"
  },
  {
    "ticker": "TSLA",
    "tweet_id": "2047701640304836817"
  },
  {
    "ticker": "TSLA",
    "tweet_id": "2047575678615507240"
  },
  {
    "ticker": "TSLA",
    "tweet_id": "2047574971774611553"
  },
  {
    "ticker": "TSLA",
    "tweet_id": "2047574398903939458"
  },
  {
    "ticker": "TSLA",
    "tweet_id": "2047571678843306248"
  },
  {
    "ticker": "TSLA",
    "tweet_id": "2047570667030323375"
  },
  {
    "ticker": "TSLA",
    "tweet_id": "2047503907350605925"
  },
  {
    "ticker": "TSLA",
    "tweet_id": "2047503364620230775"
  },
  {
    "ticker": "TSLA",
    "tweet_id": "2047503147627942302"
  },
  {
    "ticker": "TSLA",
    "tweet_id": "2047502949639958932"
  },
  {
    "ticker": "TSLA",
    "tweet_id": "2047502409728217418"
  },
  {
    "ticker": "TSLA",
    "tweet_id": "2047442415968268438"
  },
  {
    "ticker": "TSLA",
    "tweet_id": "2047421375674233228"
  },
  {
    "ticker": "TSLA",
    "tweet_id": "2047243902504390840"
  },
  {
    "ticker": "TSLA",
    "tweet_id": "2047243489159892992"
  },
  {
    "ticker": "TSLA",
    "tweet_id": "2047241857130958951"
  },
  {
    "ticker": "TSLA",
    "tweet_id": "2047241693691519452"
  },
  {
    "ticker": "TSLA",
    "tweet_id": "2047241647730364770"
  },
  {
    "ticker": "TSLA",
    "tweet_id": "2047225976208420913"
  },
  {
    "ticker": "TSLA",
    "tweet_id": "2047225397033800111"
  },
  {
    "ticker": "TSLA",
    "tweet_id": "2047224780374610091"
  },
  {
    "ticker": "TSLA",
    "tweet_id": "2047198355630260373"
  },
  {
    "ticker": "TSLA",
    "tweet_id": "2047197498218021198"
  },
  {
    "ticker": "TSLA",
    "tweet_id": "2047197306408276330"
  },
  {
    "ticker": "TSLA",
    "tweet_id": "2047190671501693389"
  },
  {
    "ticker": "TSLA",
    "tweet_id": "2047174299031642435"
  },
  {
    "ticker": "TSLA",
    "tweet_id": "2047169851655929969"
  },
  {
    "ticker": "TSLA",
    "tweet_id": "2047169704880406747"
  },
  {
    "ticker": "TSLA",
    "tweet_id": "2047167710270775465"
  },
  {
    "ticker": "TSLA",
    "tweet_id": "2047167014033043869"
  },
  {
    "ticker": "TSLA",
    "tweet_id": "2047115745113284928"
  },
  {
    "ticker": "TSLA",
    "tweet_id": "2047115457144979598"
  },
  {
    "ticker": "TSLA",
    "tweet_id": "2047115133390880999"
  },
  {
    "ticker": "TSLA",
    "tweet_id": "2047114604820447376"
  },
  {
    "ticker": "TSLA",
    "tweet_id": "2047051026587439360"
  },
  {
    "ticker": "TSLA",
    "tweet_id": "2047010640619794593"
  },
  {
    "ticker": "TSLA",
    "tweet_id": "2047010390647742735"
  },
  {
    "ticker": "TSLA",
    "tweet_id": "2047006072120955281"
  },
  {
    "ticker": "TSLA",
    "tweet_id": "2046984685113180451"
  },
  {
    "ticker": "TSLA",
    "tweet_id": "2046983806838505840"
  },
  {
    "ticker": "TSLA",
    "tweet_id": "2046983626512797778"
  },
  {
    "ticker": "TSLA",
    "tweet_id": "2046983260828303585"
  },
  {
    "ticker": "TSLA",
    "tweet_id": "2046982745088303481"
  },
  {
    "ticker": "TSLA",
    "tweet_id": "2046981493197586714"
  },
  {
    "ticker": "TSLA",
    "tweet_id": "2046976021467931076"
  },
  {
    "ticker": "TSLA",
    "tweet_id": "2046973012507832393"
  },
  {
    "ticker": "TSLA",
    "tweet_id": "2046860756331676018"
  },
  {
    "ticker": "TSLA",
    "tweet_id": "2046859778886901770"
  },
  {
    "ticker": "TSLA",
    "tweet_id": "2046859368772059569"
  },
  {
    "ticker": "TSLA",
    "tweet_id": "2046857489396744219"
  },
  {
    "ticker": "TSLA",
    "tweet_id": "2046857362787402190"
  },
  {
    "ticker": "TSLA",
    "tweet_id": "2046852198840012887"
  },
  {
    "ticker": "TSLA",
    "tweet_id": "2046848890008158293"
  },
  {
    "ticker": "TSLA",
    "tweet_id": "2046847746238218671"
  },
  {
    "ticker": "TSLA",
    "tweet_id": "2046847672137433468"
  },
  {
    "ticker": "TSLA",
    "tweet_id": "2046847589513847226"
  },
  {
    "ticker": "TSLA",
    "tweet_id": "2046847498493260212"
  },
  {
    "ticker": "TSLA",
    "tweet_id": "2046847098167910765"
  },
  {
    "ticker": "TSLA",
    "tweet_id": "2046846999962542430"
  },
  {
    "ticker": "TSLA",
    "tweet_id": "2046846861105897857"
  },
  {
    "ticker": "TSLA",
    "tweet_id": "2046845698427990199"
  },
  {
    "ticker": "TSLA",
    "tweet_id": "2046845585861300525"
  },
  {
    "ticker": "TSLA",
    "tweet_id": "2046845343220773294"
  },
  {
    "ticker": "TSLA",
    "tweet_id": "2046845250937733164"
  },
  {
    "ticker": "TSLA",
    "tweet_id": "2046844997132079441"
  },
  {
    "ticker": "TSLA",
    "tweet_id": "2046844764260127034"
  },
  {
    "ticker": "TSLA",
    "tweet_id": "2046844565848473635"
  },
  {
    "ticker": "TSLA",
    "tweet_id": "2046843538923499657"
  },
  {
    "ticker": "TSLA",
    "tweet_id": "2046843472158552238"
  },
  {
    "ticker": "TSLA",
    "tweet_id": "2046843224921104665"
  },
  {
    "ticker": "TSLA",
    "tweet_id": "2046843177483588035"
  },
  {
    "ticker": "TSLA",
    "tweet_id": "2046843023141544382"
  },
  {
    "ticker": "TSLA",
    "tweet_id": "2046842932498424277"
  },
  {
    "ticker": "TSLA",
    "tweet_id": "2046842054416777311"
  },
  {
    "ticker": "TSLA",
    "tweet_id": "2046841404844871929"
  },
  {
    "ticker": "TSLA",
    "tweet_id": "2046839153787089295"
  },
  {
    "ticker": "TSLA",
    "tweet_id": "2046752678802346288"
  },
  {
    "ticker": "TSLA",
    "tweet_id": "2046732434352357617"
  },
  {
    "ticker": "TSLA",
    "tweet_id": "2046731041545601106"
  },
  {
    "ticker": "TSLA",
    "tweet_id": "2046713957252030938"
  },
  {
    "ticker": "TSLA",
    "tweet_id": "2046617607336329447"
  },
  {
    "ticker": "TSLA",
    "tweet_id": "2046612126211457093"
  },
  {
    "ticker": "TSLA",
    "tweet_id": "2046612052442046761"
  },
  {
    "ticker": "TSLA",
    "tweet_id": "2046600658308968817"
  },
  {
    "ticker": "TSLA",
    "tweet_id": "2046600139632976191"
  },
  {
    "ticker": "TSLA",
    "tweet_id": "2046599400458178670"
  },
  {
    "ticker": "TSLA",
    "tweet_id": "2046598215047246263"
  },
  {
    "ticker": "TSLA",
    "tweet_id": "2046594456141365724"
  },
  {
    "ticker": "TSLA",
    "tweet_id": "2046456394740645926"
  },
  {
    "ticker": "TSLA",
    "tweet_id": "2046454010446582108"
  },
  {
    "ticker": "TSLA",
    "tweet_id": "2046413727239372940"
  },
  {
    "ticker": "TSLA",
    "tweet_id": "2046405057332097524"
  },
  {
    "ticker": "TSLA",
    "tweet_id": "2046404769040810159"
  },
  {
    "ticker": "TSLA",
    "tweet_id": "2046387953086140472"
  },
  {
    "ticker": "TSLA",
    "tweet_id": "2046387188535861419"
  },
  {
    "ticker": "TSLA",
    "tweet_id": "2046329674876243998"
  },
  {
    "ticker": "TSLA",
    "tweet_id": "2046328430984085688"
  },
  {
    "ticker": "TSLA",
    "tweet_id": "2046327719231705207"
  },
  {
    "ticker": "TSLA",
    "tweet_id": "2046326850415186114"
  },
  {
    "ticker": "TSLA",
    "tweet_id": "2046324618571427978"
  },
  {
    "ticker": "TSLA",
    "tweet_id": "2046313895447716230"
  },
  {
    "ticker": "TSLA",
    "tweet_id": "2046308563031867886"
  },
  {
    "ticker": "TSLA",
    "tweet_id": "2046308075947405581"
  },
  {
    "ticker": "TSLA",
    "tweet_id": "2046234586808520709"
  },
  {
    "ticker": "TSLA",
    "tweet_id": "2046234475940499745"
  },
  {
    "ticker": "TSLA",
    "tweet_id": "2046234403194499405"
  },
  {
    "ticker": "TSLA",
    "tweet_id": "2046234324643491904"
  },
  {
    "ticker": "TSLA",
    "tweet_id": "2046225819580698771"
  },
  {
    "ticker": "TSLA",
    "tweet_id": "2046225376947442011"
  },
  {
    "ticker": "TSLA",
    "tweet_id": "2046225338397528566"
  },
  {
    "ticker": "TSLA",
    "tweet_id": "2046221982778138918"
  },
  {
    "ticker": "TSLA",
    "tweet_id": "2046215996923363666"
  },
  {
    "ticker": "MSFT",
    "tweet_id": "2048165186482389253"
  },
  {
    "ticker": "MSFT",
    "tweet_id": "2048160404376105179"
  },
  {
    "ticker": "MSFT",
    "tweet_id": "2048062261584077149"
  },
  {
    "ticker": "MSFT",
    "tweet_id": "2047823357635354814"
  },
  {
    "ticker": "MSFT",
    "tweet_id": "2047787124846653895"
  },
  {
    "ticker": "MSFT",
    "tweet_id": "2047683787828703289"
  },
  {
    "ticker": "MSFT",
    "tweet_id": "2047496909452177757"
  },
  {
    "ticker": "MSFT",
    "tweet_id": "2047403771416940715"
  },
  {
    "ticker": "MSFT",
    "tweet_id": "2047395562501411058"
  },
  {
    "ticker": "MSFT",
    "tweet_id": "2047392357482639749"
  },
  {
    "ticker": "MSFT",
    "tweet_id": "2047388944677863691"
  },
  {
    "ticker": "MSFT",
    "tweet_id": "2047388773697147169"
  },
  {
    "ticker": "MSFT",
    "tweet_id": "2047386286613283180"
  },
  {
    "ticker": "MSFT",
    "tweet_id": "2047386136494879164"
  },
  {
    "ticker": "MSFT",
    "tweet_id": "2047386068194852963"
  },
  {
    "ticker": "MSFT",
    "tweet_id": "2047382023858184679"
  },
  {
    "ticker": "MSFT",
    "tweet_id": "2047379615589777666"
  },
  {
    "ticker": "MSFT",
    "tweet_id": "2047378253313106112"
  },
  {
    "ticker": "MSFT",
    "tweet_id": "2047378669627113928"
  },
  {
    "ticker": "MSFT",
    "tweet_id": "2047378431260664058"
  },
  {
    "ticker": "MSFT",
    "tweet_id": "2047378253313106112"
  },
  {
    "ticker": "MSFT",
    "tweet_id": "2047349336263012771"
  },
  {
    "ticker": "MSFT",
    "tweet_id": "2047347674743963705"
  },
  {
    "ticker": "MSFT",
    "tweet_id": "2047149494274515032"
  },
  {
    "ticker": "MSFT",
    "tweet_id": "2047017964105597009"
  },
  {
    "ticker": "MSFT",
    "tweet_id": "2047007669324804427"
  },
  {
    "ticker": "MSFT",
    "tweet_id": "2046752492093165708"
  },
  {
    "ticker": "MSFT",
    "tweet_id": "2046682384251429279"
  },
  {
    "ticker": "MSFT",
    "tweet_id": "2046672912833458597"
  },
  {
    "ticker": "MSFT",
    "tweet_id": "2046671254586023982"
  },
  {
    "ticker": "MSFT",
    "tweet_id": "2046604989527912590"
  },
  {
    "ticker": "MSFT",
    "tweet_id": "2046598595869331894"
  },
  {
    "ticker": "MSFT",
    "tweet_id": "2046330825265086712"
  },
  {
    "ticker": "MSFT",
    "tweet_id": "2046330082726384051"
  },
  {
    "ticker": "MSFT",
    "tweet_id": "2045523881012981785"
  },
  {
    "ticker": "MSFT",
    "tweet_id": "2044921348540264614"
  },
  {
    "ticker": "MSFT",
    "tweet_id": "2044920923078447296"
  },
  {
    "ticker": "MSFT",
    "tweet_id": "2044920562901021107"
  },
  {
    "ticker": "MSFT",
    "tweet_id": "2044920514205139430"
  },
  {
    "ticker": "MSFT",
    "tweet_id": "2044858929491202435"
  },
  {
    "ticker": "MSFT",
    "tweet_id": "2044858862042591378"
  },
  {
    "ticker": "MSFT",
    "tweet_id": "2042738954550603884"
  },
  {
    "ticker": "MSFT",
    "tweet_id": "2042342572958630332"
  },
  {
    "ticker": "MSFT",
    "tweet_id": "2041918495961804802"
  },
  {
    "ticker": "MSFT",
    "tweet_id": "2041658719839383945"
  },
  {
    "ticker": "MSFT",
    "tweet_id": "2041186468010545331"
  },
  {
    "ticker": "MSFT",
    "tweet_id": "2039773754801422750"
  },
  {
    "ticker": "MSFT",
    "tweet_id": "2039773740586918137"
  },
  {
    "ticker": "MSFT",
    "tweet_id": "2038640963036626971"
  },
  {
    "ticker": "MSFT",
    "tweet_id": "2037610000122839116"
  },
  {
    "ticker": "MSFT",
    "tweet_id": "2037396826060673188"
  },
  {
    "ticker": "MSFT",
    "tweet_id": "2036558551825653810"
  },
  {
    "ticker": "MSFT",
    "tweet_id": "2036489823792607273"
  },
  {
    "ticker": "MSFT",
    "tweet_id": "2036488680769241223"
  },
  {
    "ticker": "MSFT",
    "tweet_id": "2036137695605563682"
  },
  {
    "ticker": "MSFT",
    "tweet_id": "2033935276079510011"
  },
  {
    "ticker": "MSFT",
    "tweet_id": "2033660522961502288"
  },
  {
    "ticker": "MSFT",
    "tweet_id": "2033659889843913000"
  },
  {
    "ticker": "MSFT",
    "tweet_id": "2033659246542524566"
  },
  {
    "ticker": "MSFT",
    "tweet_id": "2033659170088751372"
  },
  {
    "ticker": "MSFT",
    "tweet_id": "2033599554508230908"
  },
  {
    "ticker": "MSFT",
    "tweet_id": "2033599375256207820"
  },
  {
    "ticker": "MSFT",
    "tweet_id": "2030326937869242487"
  },
  {
    "ticker": "MSFT",
    "tweet_id": "2030319489993298349"
  },
  {
    "ticker": "MSFT",
    "tweet_id": "2030318958512164966"
  },
  {
    "ticker": "MSFT",
    "tweet_id": "2030318632899953108"
  },
  {
    "ticker": "MSFT",
    "tweet_id": "2030318481653334067"
  },
  {
    "ticker": "MSFT",
    "tweet_id": "2030318213482131670"
  },
  {
    "ticker": "MSFT",
    "tweet_id": "2029627696314208257"
  },
  {
    "ticker": "MSFT",
    "tweet_id": "2029623948980416681"
  },
  {
    "ticker": "MSFT",
    "tweet_id": "2029623747028885529"
  },
  {
    "ticker": "MSFT",
    "tweet_id": "2029623487007183274"
  },
  {
    "ticker": "MSFT",
    "tweet_id": "2029622732594499630"
  },
  {
    "ticker": "MSFT",
    "tweet_id": "2028640354912923739"
  },
  {
    "ticker": "MSFT",
    "tweet_id": "2027900042720498089"
  },
  {
    "ticker": "MSFT",
    "tweet_id": "2027900042720498089"
  },
  {
    "ticker": "MSFT",
    "tweet_id": "2027909609323958710"
  },
  {
    "ticker": "MSFT",
    "tweet_id": "2027905510578761820"
  },
  {
    "ticker": "MSFT",
    "tweet_id": "2027850288959525125"
  },
  {
    "ticker": "MSFT",
    "tweet_id": "2027578652477821175"
  },
  {
    "ticker": "MSFT",
    "tweet_id": "2027578580159631610"
  },
  {
    "ticker": "MSFT",
    "tweet_id": "2027578508042723599"
  },
  {
    "ticker": "MSFT",
    "tweet_id": "2027386252555919386"
  },
  {
    "ticker": "MSFT",
    "tweet_id": "2027087700214591913"
  },
  {
    "ticker": "MSFT",
    "tweet_id": "2027087689359753483"
  },
  {
    "ticker": "MSFT",
    "tweet_id": "2027087128514183553"
  },
  {
    "ticker": "MSFT",
    "tweet_id": "2024826822060290508"
  },
  {
    "ticker": "MSFT",
    "tweet_id": "2023852667454583150"
  },
  {
    "ticker": "MSFT",
    "tweet_id": "2023839310764802349"
  },
  {
    "ticker": "MSFT",
    "tweet_id": "2023838999341920283"
  },
  {
    "ticker": "MSFT",
    "tweet_id": "2023463428892094655"
  },
  {
    "ticker": "MSFT",
    "tweet_id": "2023453083595141411"
  },
  {
    "ticker": "MSFT",
    "tweet_id": "2023233085509410833"
  },
  {
    "ticker": "MSFT",
    "tweet_id": "2023150230905159801"
  },
  {
    "ticker": "MSFT",
    "tweet_id": "2022729068949717182"
  },
  {
    "ticker": "MSFT",
    "tweet_id": "2022564958542942510"
  },
  {
    "ticker": "MSFT",
    "tweet_id": "2022564504232722838"
  },
  {
    "ticker": "MSFT",
    "tweet_id": "2022564381306089684"
  },
  {
    "ticker": "MSFT",
    "tweet_id": "2022011797524582726"
  },
  {
    "ticker": "MSFT",
    "tweet_id": "2021986904481419463"
  },
  {
    "ticker": "MSFT",
    "tweet_id": "2021984777470193767"
  },
  {
    "ticker": "MSFT",
    "tweet_id": "2021606985469211065"
  },
  {
    "ticker": "MSFT",
    "tweet_id": "2021452911511998557"
  },
  {
    "ticker": "MSFT",
    "tweet_id": "2021451413910663556"
  },
  {
    "ticker": "MSFT",
    "tweet_id": "2020977975081177343"
  },
  {
    "ticker": "MSFT",
    "tweet_id": "2020941091114295520"
  },
  {
    "ticker": "MSFT",
    "tweet_id": "2020940847190356092"
  },
  {
    "ticker": "MSFT",
    "tweet_id": "2020899100833787913"
  },
  {
    "ticker": "MSFT",
    "tweet_id": "2020881268435747075"
  },
  {
    "ticker": "MSFT",
    "tweet_id": "2020876034313531581"
  },
  {
    "ticker": "MSFT",
    "tweet_id": "2020866693564625219"
  },
  {
    "ticker": "MSFT",
    "tweet_id": "2020866257612935359"
  },
  {
    "ticker": "MSFT",
    "tweet_id": "2020686203205599366"
  },
  {
    "ticker": "MSFT",
    "tweet_id": "2020678853468053516"
  },
  {
    "ticker": "MSFT",
    "tweet_id": "2020677993673433330"
  },
  {
    "ticker": "MSFT",
    "tweet_id": "2019814741129195576"
  },
  {
    "ticker": "MSFT",
    "tweet_id": "2019813802049696064"
  },
  {
    "ticker": "MSFT",
    "tweet_id": "2019812793491632567"
  },
  {
    "ticker": "MSFT",
    "tweet_id": "2019812576482517322"
  },
  {
    "ticker": "MSFT",
    "tweet_id": "2019533972263563566"
  },
  {
    "ticker": "MSFT",
    "tweet_id": "2019475551719977453"
  },
  {
    "ticker": "MSFT",
    "tweet_id": "2019474754529321247"
  },
  {
    "ticker": "MSFT",
    "tweet_id": "2019442016594088211"
  },
  {
    "ticker": "MSFT",
    "tweet_id": "2019441198734209374"
  },
  {
    "ticker": "MSFT",
    "tweet_id": "2019219967250669741"
  },
  {
    "ticker": "MSFT",
    "tweet_id": "2019139765015310773"
  },
  {
    "ticker": "MSFT",
    "tweet_id": "2019139174339928189"
  },
  {
    "ticker": "MSFT",
    "tweet_id": "2018813527780463027"
  },
  {
    "ticker": "MSFT",
    "tweet_id": "2018812624910291186"
  },
  {
    "ticker": "MSFT",
    "tweet_id": "2018809497603743824"
  },
  {
    "ticker": "MSFT",
    "tweet_id": "2018734731437985930"
  },
  {
    "ticker": "MSFT",
    "tweet_id": "2018451015272694248"
  },
  {
    "ticker": "MSFT",
    "tweet_id": "2018444309750862333"
  },
  {
    "ticker": "MSFT",
    "tweet_id": "2018443522043756973"
  },
  {
    "ticker": "MSFT",
    "tweet_id": "2018437537103269909"
  },
  {
    "ticker": "MSFT",
    "tweet_id": "2018414858015039504"
  },
  {
    "ticker": "MSFT",
    "tweet_id": "2018414490237468944"
  },
  {
    "ticker": "MSFT",
    "tweet_id": "2018414465310707956"
  },
  {
    "ticker": "MSFT",
    "tweet_id": "2015548504194654707"
  },
  {
    "ticker": "MSFT",
    "tweet_id": "2014733975755817267"
  },
  {
    "ticker": "MSFT",
    "tweet_id": "2014399391025574308"
  },
  {
    "ticker": "MSFT",
    "tweet_id": "2013703158459978076"
  },
  {
    "ticker": "MSFT",
    "tweet_id": "2013405667235598565"
  },
  {
    "ticker": "MSFT",
    "tweet_id": "2013403329322242261"
  },
  {
    "ticker": "MSFT",
    "tweet_id": "2012271781394989327"
  },
  {
    "ticker": "MSFT",
    "tweet_id": "2012266814508556305"
  },
  {
    "ticker": "MSFT",
    "tweet_id": "2012253252771824074"
  },
  {
    "ticker": "MSFT",
    "tweet_id": "2012243893744443706"
  },
  {
    "ticker": "MSFT",
    "tweet_id": "2012242952542683227"
  },
  {
    "ticker": "MSFT",
    "tweet_id": "2011490615985414382"
  },
  {
    "ticker": "MSFT",
    "tweet_id": "2009009270067745225"
  },
  {
    "ticker": "MSFT",
    "tweet_id": "2007149715671163020"
  },
  {
    "ticker": "MSFT",
    "tweet_id": "2004939524216910323"
  },
  {
    "ticker": "MSFT",
    "tweet_id": "2004173599893327972"
  },
  {
    "ticker": "MSFT",
    "tweet_id": "2003419371432214548"
  },
  {
    "ticker": "MSFT",
    "tweet_id": "2002183936777072789"
  },
  {
    "ticker": "MSFT",
    "tweet_id": "2001816114595270921"
  },
  {
    "ticker": "MSFT",
    "tweet_id": "2001729046359556371"
  },
  {
    "ticker": "MSFT",
    "tweet_id": "2001724828567400700"
  },
  {
    "ticker": "MSFT",
    "tweet_id": "2001724019188408352"
  },
  {
    "ticker": "MSFT",
    "tweet_id": "2000998310082195496"
  },
  {
    "ticker": "MSFT",
    "tweet_id": "2000997906078388332"
  },
  {
    "ticker": "MSFT",
    "tweet_id": "2000980694588383434"
  },
  {
    "ticker": "MSFT",
    "tweet_id": "2000970131741270383"
  },
  {
    "ticker": "MSFT",
    "tweet_id": "2000970117740683397"
  },
  {
    "ticker": "MSFT",
    "tweet_id": "2000960108608815504"
  },
  {
    "ticker": "MSFT",
    "tweet_id": "2000733176491336035"
  },
  {
    "ticker": "MSFT",
    "tweet_id": "1999624463013544024"
  },
  {
    "ticker": "MSFT",
    "tweet_id": "1999232754131804249"
  },
  {
    "ticker": "MSFT",
    "tweet_id": "1999232267915534380"
  },
  {
    "ticker": "MSFT",
    "tweet_id": "1999230523827446193"
  },
  {
    "ticker": "MSFT",
    "tweet_id": "1999230400313589874"
  },
  {
    "ticker": "MSFT",
    "tweet_id": "1999192990171169145"
  },
  {
    "ticker": "MSFT",
    "tweet_id": "1999191794274492691"
  }
]